calltracer/__init__.py
calltracer/calltracer.py
calltracer/richlogging.py
examples/aex.py
examples/ex.py
examples/rex.py
pytracecall-4.2.3.dist-info/licenses/LICENSE
tests/test_act.py
tests/test_ct.py
tests/test_rich.py
pytracecall-4.2.3.dist-info/METADATA
pytracecall-4.2.3.dist-info/WHEEL
pytracecall-4.2.3.dist-info/top_level.txt
pytracecall-4.2.3.dist-info/RECORD
