Metadata-Version: 2.4
Name: pytracecall
Version: 4.2.3
Summary: pytracecall: A debugging module with sync and async decorators (CallTracer and aCallTracer) for tracing function calls, and a function (stack) for logging the current call stack
Author-email: Alex Semenyaka <alex.semenyaka@gmail.com>
License: MIT
Project-URL: Homepage, https://github.com/alexsemenyaka/calltracer
Project-URL: Repository, https://github.com/alexsemenyaka/calltracer.git
Project-URL: Issues, https://github.com/alexsemenyaka/calltracer/issues
Keywords: debug,debugging,trace,tracer,decorator,logging,stacktrace,callstack,inspect,recursion
Classifier: Intended Audience :: Developers
Classifier: Programming Language :: Python :: 3
Classifier: License :: OSI Approved :: MIT License
Classifier: Operating System :: OS Independent
Classifier: Intended Audience :: Developers
Classifier: Programming Language :: Python :: 3
Classifier: Programming Language :: Python :: 3.10
Classifier: Programming Language :: Python :: 3.11
Classifier: Programming Language :: Python :: 3.12
Classifier: Programming Language :: Python :: 3.13
Classifier: Topic :: Software Development :: Libraries :: Python Modules
Classifier: Topic :: Software Development :: Debuggers
Classifier: Topic :: System :: Logging
Requires-Python: >=3.8
License-File: LICENSE
Provides-Extra: rich
Requires-Dist: rich>=13.0.0; extra == "rich"
Dynamic: license-file
